{"cameraMode":{"drawMode":0,"name":"Shaded","section":"Shading Mode"},"sceneLighting":false,"audioPlay":false,"sceneViewState":{"m_AlwaysRefresh":false,"showFog":true,"showSkybox":false,"showFlares":true,"showImageEffects":true,"showParticleSystems":true,"showVisualEffectGraphs":true,"m_FxEnabled":true},"in2DMode":false,"pivot":{"x":1.7674264907836915,"y":8.145092964172364,"z":-4.047088623046875},"rotation":{"x":-0.10748352855443955,"y":-0.7414305210113525,"z":0.1223711147904396,"w":-0.6510227918624878},"size":7.971418857574463,"orthographic":false}